git_send_telegram/__init__.py
wldhx_git_send_telegram-0.1.2.dist-info/entry_points.txt
wldhx_git_send_telegram-0.1.2.dist-info/LICENSE
wldhx_git_send_telegram-0.1.2.dist-info/WHEEL
wldhx_git_send_telegram-0.1.2.dist-info/METADATA
wldhx_git_send_telegram-0.1.2.dist-info/RECORD
