Metadata-Version: 2.1
Name: wldhx-git-send-telegram
Version: 0.1.2
Summary: Your git send-email for 2023!
Home-page: https://git.sr.ht/~wldhx/git-send-telegram
License: AGPL-3.0-or-later
Author: wldhx
Author-email: wldhx+pypi_python_org@wldhx.me
Requires-Python: >=3.10,<4.0
Classifier: License :: OSI Approved :: GNU Affero General Public License v3 or later (AGPLv3+)
Classifier: Programming Language :: Python :: 3
Classifier: Programming Language :: Python :: 3.10
Classifier: Programming Language :: Python :: 3.11
Requires-Dist: gitpython (>=3.1.29,<4.0.0)
Requires-Dist: pyrogram (>=2.0.64,<3.0.0)
Requires-Dist: tgcrypto (>=1.2.5,<2.0.0)
Project-URL: Repository, https://git.sr.ht/~wldhx/git-send-telegram
